kito/__init__.py
kito/custom_model_test_bench.py
kito/test_bench.py
kito/tst_bench.py
kito-1.0.5.dist-info/LICENSE
kito-1.0.5.dist-info/METADATA
kito-1.0.5.dist-info/WHEEL
kito-1.0.5.dist-info/top_level.txt
kito-1.0.5.dist-info/RECORD
