Metadata-Version: 2.1
Name: kito
Version: 1.0.5
Summary: Keras inference time optimizer
Home-page: https://github.com/ZFTurbo/Keras-inference-time-optimizer
Author: Roman Sol (ZFTurbo)
Author-email: UNKNOWN
License: MIT License
Platform: UNKNOWN
Requires-Dist: keras
Requires-Dist: numpy
